quine_mccluskey/__init__.py
quine_mccluskey/qm.py
tests/__init__.py
tests/test.py
quine_mccluskey-0.3.dist-info/LICENSE
quine_mccluskey-0.3.dist-info/METADATA
quine_mccluskey-0.3.dist-info/WHEEL
quine_mccluskey-0.3.dist-info/top_level.txt
quine_mccluskey-0.3.dist-info/RECORD
