Metadata-Version: 2.1
Name: quine-mccluskey
Version: 0.3
Summary: An implementation of the Quine-McCluskey algorithm
Home-page: https://github.com/tpircher/quine-mccluskey
Author: Thomas Pircher
Author-email: tehpeh-web@tty1.net
License: BSD
Download-URL: https://github.com/tpircher/quine-mccluskey/releases/tag/v0.3
Keywords: Quine McCluskey,XOR
Platform: UNKNOWN
Classifier: Development Status :: 4 - Beta
Classifier: Topic :: Utilities
Classifier: License :: OSI Approved :: MIT License
